xsterminal/__init__.py
xsterminal-1.0.1.dist-info/METADATA
xsterminal-1.0.1.dist-info/RECORD
xsterminal-1.0.1.dist-info/WHEEL
xsterminal-1.0.1.dist-info/top_level.txt
