Metadata-Version: 2.1
Name: xsterminal
Version: 1.0.1
Summary: xs get data
Home-page: UNKNOWN
Author: ngxs
Author-email: 717719075@qq.com
License: MIT
Platform: UNKNOWN
Requires-Dist: requests
Requires-Dist: pandas
